<?xml version="1.0" encoding="utf-8"?>
<manifestConfig xmlns:android="http://schemas.android.com/apk/res/android">
    <applicationCfg keyword="com.AdChina.plugin">
        <activity android:label="@string/app_name" android:theme="@android:style/Theme.Translucent"
            android:configChanges="orientation|keyboard|keyboardHidden|screenSize"
            android:name="com.adchina.android.ads.views.AdBrowserView">
        </activity>
        <receiver
            android:name="com.adchina.android.ads.views.AdCompleteReceiver">
            <intent-filter>
                <action android:name="android.intent.action.DOWNLOAD_COMPLETE"/>
            </intent-filter>
        </receiver>
    </applicationCfg>
    
    <permissionCfg>
        <uses-permission android:name="android.permission.INTERNET"/>
        <uses-permission android:name="android.permission.READ_PHONE_STATE"/>
        <uses-permission android:name="android.permission.ACCESS_NETWORK_STATE"/>
        <uses-permission android:name="android.permission.ACCESS_WIFI_STATE" />
        <uses-permission android:name="android.permission.ACCESS_COARSE_LOCATION"/>
        <uses-permission android:name="android.permission.ACCESS_FINE_LOCATION" />
        <uses-permission android:name="android.permission.READ_EXTERNAL_STORAGE" />
        <uses-permission android:name="android.permission.WRITE_EXTERNAL_STORAGE"/>
        <uses-permission android:name="android.permission.READ_CALENDAR"/>
        <uses-permission android:name="android.permission.WRITE_CALENDAR"/>
        <uses-permission android:name="android.permission.RECORD_AUDIO"/>
        <uses-permission android:name="com.android.launcher.permission.INSTALL_SHORTCUT"/>
        <uses-permission android:name="android.permission.VIBRATE"/>
    </permissionCfg>
</manifestConfig> 
